{"frameRate":30,"name":"gameplay_revive_countdown_model","version":"5.5","compatibleVersion":"5.5","armature":[{"type":"Armature","frameRate":30,"name":"Armature","aabb":{"x":-141,"y":-147.55,"width":282,"height":282},"bone":[{"name":"root"},{"name":"up","parent":"root","transform":{"y":0.8568}},{"name":"ty2","parent":"root","transform":{"y":-6.5527}},{"name":"ty","parent":"root","transform":{"x":50.2346,"y":10.1686,"scX":1.3,"scY":1.3}},{"name":"ty2_2","parent":"root","transform":{"x":-15.6897,"y":46.7579,"scX":1.65,"scY":1.65}},{"name":"ty_3","parent":"root","transform":{"x":-15.6897,"y":-48.6924,"scX":1.9,"scY":1.9}}],"slot":[{"name":"ty2","parent":"ty2"},{"name":"ty","parent":"ty"},{"name":"ty_2","parent":"ty2_2"},{"name":"ty_3","parent":"ty_3"},{"name":"up","parent":"up"},{"name":"down","parent":"up"}],"skin":[{"slot":[{"name":"down","display":[{"name":"5","transform":{"skX":-0.07,"skY":-0.07},"path":"down_5"},{"name":"4","transform":{"x":-3.96,"y":-10.3},"path":"down_4"},{"name":"0","path":"down_0"},{"name":"1","path":"down_1"},{"name":"2","path":"down_2"},{"name":"3","path":"down_3"}]},{"name":"ty","display":[{"name":"ty"}]},{"name":"ty2","display":[{"name":"ty2"}]},{"name":"ty_3","display":[{"name":"ty"}]},{"name":"up","display":[{"name":"5","path":"up_5"},{"name":"4","transform":{"x":-3.96,"y":-10.3},"path":"up_4"},{"name":"0","path":"up_0"},{"name":"1","path":"up_1"},{"name":"2","path":"up_2"},{"name":"3","path":"up_3"}]},{"name":"ty_2","display":[{"name":"ty"}]}]}],"animation":[{"duration":172,"playTimes":0,"name":"newAnimation_1","bone":[{"name":"up","scaleFrame":[{"duration":30},{"duration":4,"curve":[0,0,0.5,1]},{"duration":4,"curve":[0.5,0,1,1],"x":1.2,"y":1.2},{"duration":22},{"duration":4,"curve":[0,0,0.5,1]},{"duration":4,"curve":[0.5,0,1,1],"x":1.2,"y":1.2},{"duration":22},{"duration":4,"curve":[0,0,0.5,1]},{"duration":4,"curve":[0.5,0,1,1],"x":1.2,"y":1.2},{"duration":22},{"duration":4,"curve":[0,0,0.5,1]},{"duration":4,"curve":[0.5,0,1,1],"x":1.2,"y":1.2},{"duration":22},{"duration":4,"curve":[0,0,0.5,1]},{"duration":4,"curve":[0.5,0,1,1],"x":1.2,"y":1.2},{"duration":14}]}],"slot":[{"name":"up","displayFrame":[{"duration":172,"value":-1}]},{"name":"ty2","displayFrame":[{"duration":172,"value":-1}]},{"name":"ty","displayFrame":[{"duration":172,"value":-1}]},{"name":"ty_2","displayFrame":[{"duration":172,"value":-1}]},{"name":"ty_3","displayFrame":[{"duration":172,"value":-1}]},{"name":"down","displayFrame":[{"duration":30},{"duration":30,"value":1},{"duration":30,"value":5},{"duration":30,"value":4},{"duration":30,"value":3},{"duration":22,"value":2}]}]},{"duration":172,"playTimes":0,"name":"newAnimation_3","bone":[{"name":"ty2","scaleFrame":[{"duration":30},{"duration":4,"tweenEasing":0},{"duration":8,"tweenEasing":0,"x":1.2,"y":1.2},{"duration":18},{"duration":4,"tweenEasing":0},{"duration":8,"tweenEasing":0,"x":1.2,"y":1.2},{"duration":18},{"duration":4,"tweenEasing":0},{"duration":8,"tweenEasing":0,"x":1.2,"y":1.2},{"duration":18},{"duration":4,"tweenEasing":0},{"duration":8,"tweenEasing":0,"x":1.2,"y":1.2},{"duration":18},{"duration":4,"tweenEasing":0},{"duration":8,"tweenEasing":0,"x":1.2,"y":1.2},{"duration":10}]},{"name":"ty","translateFrame":[{"duration":30},{"duration":14,"curve":[0,0,0.5,1]},{"duration":16,"x":85.11,"y":27.36},{"duration":14,"curve":[0,0,0.5,1],"y":-40.41},{"duration":16,"x":52.02,"y":-56.95},{"duration":14,"curve":[0,0,0.5,1]},{"duration":16,"x":85.11,"y":27.36},{"duration":14,"curve":[0,0,0.5,1],"y":-40.41},{"duration":16,"x":52.02,"y":-56.95},{"duration":14,"curve":[0,0,0.5,1]},{"duration":8,"x":85.11,"y":27.36}],"scaleFrame":[{"duration":30},{"duration":14,"tweenEasing":0},{"duration":16,"x":0.01,"y":0.01},{"duration":14,"tweenEasing":0},{"duration":16,"x":0.01,"y":0.01},{"duration":14,"tweenEasing":0},{"duration":16,"x":0.01,"y":0.01},{"duration":14,"tweenEasing":0},{"duration":16,"x":0.01,"y":0.01},{"duration":14,"tweenEasing":0},{"duration":8,"x":0.01,"y":0.01}]},{"name":"ty2_2","translateFrame":[{"duration":30},{"duration":17,"curve":[0,0,0.5,1]},{"duration":13,"x":-79.12,"y":27.36},{"duration":17,"curve":[0,0,0.5,1],"x":18.9},{"duration":13,"x":13.72,"y":65.54},{"duration":17,"curve":[0,0,0.5,1]},{"duration":13,"x":-79.12,"y":27.36},{"duration":17,"curve":[0,0,0.5,1],"x":18.9},{"duration":13,"x":13.72,"y":65.54},{"duration":17,"curve":[0,0,0.5,1]},{"duration":5,"x":-79.12,"y":27.36}],"scaleFrame":[{"duration":30},{"duration":17,"tweenEasing":0},{"duration":13,"x":0.01,"y":0.01},{"duration":17,"tweenEasing":0},{"duration":13,"x":0.01,"y":0.01},{"duration":17,"tweenEasing":0},{"duration":13,"x":0.01,"y":0.01},{"duration":17,"tweenEasing":0},{"duration":13,"x":0.01,"y":0.01},{"duration":17,"tweenEasing":0},{"duration":5,"x":0.01,"y":0.01}]},{"name":"ty_3","translateFrame":[{"duration":30},{"duration":15,"curve":[0,0,0.5,1]},{"duration":15,"x":-46.03,"y":-18.45},{"duration":15,"curve":[0,0,0.5,1],"y":45.82},{"duration":15,"x":-70.22,"y":32.45},{"duration":15,"curve":[0,0,0.5,1]},{"duration":15,"x":-46.03,"y":-18.45},{"duration":15,"curve":[0,0,0.5,1],"y":45.82},{"duration":15,"x":-70.22,"y":32.45},{"duration":15,"curve":[0,0,0.5,1]},{"duration":7,"x":-46.03,"y":-18.45}],"scaleFrame":[{"duration":30},{"duration":15,"tweenEasing":0},{"duration":15,"x":0.01,"y":0.01},{"duration":15,"tweenEasing":0},{"duration":15,"x":0.01,"y":0.01},{"duration":15,"tweenEasing":0},{"duration":15,"x":0.01,"y":0.01},{"duration":15,"tweenEasing":0},{"duration":15,"x":0.01,"y":0.01},{"duration":15,"tweenEasing":0},{"duration":7,"x":0.01,"y":0.01}]}],"slot":[{"name":"up","displayFrame":[{"duration":172,"value":-1}]},{"name":"ty2","displayFrame":[{"duration":30,"value":-1},{"duration":142}],"colorFrame":[{"duration":30},{"duration":4,"tweenEasing":0,"value":{"aM":0}},{"duration":8,"tweenEasing":0,"value":{"aM":67}},{"duration":18,"value":{"aM":0}},{"duration":4,"tweenEasing":0,"value":{"aM":0}},{"duration":8,"tweenEasing":0,"value":{"aM":67}},{"duration":18,"value":{"aM":0}},{"duration":4,"tweenEasing":0,"value":{"aM":0}},{"duration":8,"tweenEasing":0,"value":{"aM":67}},{"duration":18,"value":{"aM":0}},{"duration":4,"tweenEasing":0,"value":{"aM":0}},{"duration":8,"tweenEasing":0,"value":{"aM":67}},{"duration":18,"value":{"aM":0}},{"duration":4,"tweenEasing":0,"value":{"aM":0}},{"duration":8,"tweenEasing":0,"value":{"aM":67}},{"duration":10,"value":{"aM":0}}]},{"name":"ty","displayFrame":[{"duration":30,"value":-1},{"duration":142}],"colorFrame":[{"duration":34},{"duration":10,"tweenEasing":0},{"duration":20,"value":{"aM":0}},{"duration":10,"tweenEasing":0},{"duration":20,"value":{"aM":0}},{"duration":10,"tweenEasing":0},{"duration":20,"value":{"aM":0}},{"duration":10,"tweenEasing":0},{"duration":20,"value":{"aM":0}},{"duration":10,"tweenEasing":0},{"duration":8,"value":{"aM":0}}]},{"name":"ty_2","displayFrame":[{"duration":30,"value":-1},{"duration":142}],"colorFrame":[{"duration":34},{"duration":13,"tweenEasing":0},{"duration":17,"value":{"aM":0}},{"duration":13,"tweenEasing":0},{"duration":17,"value":{"aM":0}},{"duration":13,"tweenEasing":0},{"duration":17,"value":{"aM":0}},{"duration":13,"tweenEasing":0},{"duration":17,"value":{"aM":0}},{"duration":13,"tweenEasing":0},{"duration":5,"value":{"aM":0}}]},{"name":"ty_3","displayFrame":[{"duration":30,"value":-1},{"duration":142}],"colorFrame":[{"duration":34},{"duration":11,"tweenEasing":0},{"duration":19,"value":{"aM":0}},{"duration":11,"tweenEasing":0},{"duration":19,"value":{"aM":0}},{"duration":11,"tweenEasing":0},{"duration":19,"value":{"aM":0}},{"duration":11,"tweenEasing":0},{"duration":19,"value":{"aM":0}},{"duration":11,"tweenEasing":0},{"duration":7,"value":{"aM":0}}]},{"name":"down","displayFrame":[{"duration":172,"value":-1}]}]},{"duration":172,"playTimes":0,"name":"newAnimation_2","bone":[{"name":"up","scaleFrame":[{"duration":30},{"duration":4,"curve":[0,0,0.5,1]},{"duration":4,"curve":[0.5,0,1,1],"x":1.2,"y":1.2},{"duration":22},{"duration":4,"curve":[0,0,0.5,1]},{"duration":4,"curve":[0.5,0,1,1],"x":1.2,"y":1.2},{"duration":22},{"duration":4,"curve":[0,0,0.5,1]},{"duration":4,"curve":[0.5,0,1,1],"x":1.2,"y":1.2},{"duration":22},{"duration":4,"curve":[0,0,0.5,1]},{"duration":4,"curve":[0.5,0,1,1],"x":1.2,"y":1.2},{"duration":22},{"duration":4,"curve":[0,0,0.5,1]},{"duration":4,"curve":[0.5,0,1,1],"x":1.2,"y":1.2},{"duration":14}]}],"slot":[{"name":"up","displayFrame":[{"duration":30},{"duration":30,"value":1},{"duration":30,"value":5},{"duration":30,"value":4},{"duration":30,"value":3},{"duration":22,"value":2}]},{"name":"ty2","displayFrame":[{"duration":172,"value":-1}]},{"name":"ty","displayFrame":[{"duration":172,"value":-1}]},{"name":"ty_2","displayFrame":[{"duration":172,"value":-1}]},{"name":"ty_3","displayFrame":[{"duration":172,"value":-1}]},{"name":"down","displayFrame":[{"duration":172,"value":-1}]}]}],"defaultActions":[{"gotoAndPlay":"newAnimation_1"}]}]}