{"width": 512, "SubTexture": [{"width": 134, "y": 1, "height": 134, "name": "mb_29", "x": 175}, {"width": 172, "y": 1, "height": 178, "name": "JS_5", "x": 1}, {"width": 115, "y": 137, "height": 91, "name": "JS_11", "x": 175}, {"width": 68, "y": 181, "height": 69, "name": "JS_13", "x": 74}, {"width": 67, "y": 1, "height": 94, "name": "JS_15", "x": 311}, {"width": 74, "y": 137, "height": 91, "name": "JS_17", "x": 393}, {"width": 71, "y": 181, "height": 69, "name": "JS_19", "x": 1}, {"width": 65, "y": 1, "height": 67, "name": "JS_21", "x": 380}, {"width": 99, "y": 137, "height": 96, "name": "JS_23", "x": 292}, {"width": 1, "y": 100, "height": 1, "name": "mb_32", "x": 487}, {"width": 22, "y": 1, "height": 65, "name": "JLWZ_54", "x": 471}, {"width": 22, "y": 1, "height": 65, "name": "JLWZ_55", "x": 447}, {"width": 22, "y": 181, "height": 65, "name": "JLWZ_56", "x": 144}, {"width": 42, "y": 70, "height": 38, "name": "JLWZ_57", "x": 443}, {"width": 42, "y": 110, "height": 28, "name": "JLWZ_58", "x": 469}, {"width": 42, "y": 140, "height": 28, "name": "JLWZ_59", "x": 469}, {"width": 51, "y": 97, "height": 33, "name": "JLWZ_60", "x": 311}, {"width": 61, "y": 70, "height": 60, "name": "JS_27", "x": 380}, {"width": 42, "y": 170, "height": 28, "name": "JS_26", "x": 469}, {"width": 23, "y": 68, "height": 30, "name": "mb_36", "x": 487}, {"width": 22, "y": 200, "height": 29, "name": "mb_37", "x": 469}], "height": 256, "name": "jindutiao", "imagePath": "jindutiao_tex.png"}